sqlalchemy_exasol/__init__.py
sqlalchemy_exasol/base.py
sqlalchemy_exasol/constraints.py
sqlalchemy_exasol/requirements.py
sqlalchemy_exasol/types.py
sqlalchemy_exasol/util.py
sqlalchemy_exasol/version.py
sqlalchemy_exasol/warnings.py
sqlalchemy_exasol/websocket.py
sqlalchemy_exasol-6.0.0.dist-info/LICENSE
sqlalchemy_exasol-6.0.0.dist-info/METADATA
sqlalchemy_exasol-6.0.0.dist-info/WHEEL
sqlalchemy_exasol-6.0.0.dist-info/entry_points.txt
sqlalchemy_exasol-6.0.0.dist-info/RECORD
