Metadata-Version: 2.3
Name: sqlalchemy_exasol
Version: 6.0.0
Summary: EXASOL dialect for SQLAlchemy
License: BSD
Keywords: exasol,sql,sqlalchemy,data science,database
Author: Exasol AG
Author-email: opensource@exasol.com
Requires-Python: >=3.10,<3.14
Classifier: Development Status :: 5 - Production/Stable
Classifier: Intended Audience :: Developers
Classifier: Intended Audience :: Education
Classifier: Intended Audience :: Information Technology
Classifier: License :: Other/Proprietary License
Classifier: Operating System :: POSIX :: Linux
Classifier: Programming Language :: Python :: 3
Classifier: Programming Language :: Python :: 3.10
Classifier: Programming Language :: Python :: 3.11
Classifier: Programming Language :: Python :: 3.12
Classifier: Programming Language :: Python :: 3.13
Classifier: Programming Language :: Python :: 3.14
Classifier: Programming Language :: SQL
Classifier: Topic :: Database
Classifier: Topic :: Scientific/Engineering :: Information Analysis
Classifier: Topic :: Software Development
Classifier: Topic :: Software Development :: Libraries
Classifier: Topic :: Software Development :: Libraries :: Application Frameworks
Classifier: Topic :: Software Development :: Libraries :: Python Modules
Requires-Dist: packaging (>=21.3)
Requires-Dist: pyexasol (>=0.26.0,<2)
Requires-Dist: sqlalchemy (>=2.0.0,<3.0.0)
Project-URL: Changelog, https://exasol.github.io/sqlalchemy-exasol/changelog.html
Project-URL: Documentation, https://exasol.github.io/sqlalchemy-exasol/
Project-URL: Homepage, https://www.exasol.com/
Project-URL: Issues, https://github.com/exasol/sqlalchemy-exasol/issues
Project-URL: Source, https://github.com/exasol/sqlalchemy-exasol
